nwpm/__init__.py
nwpm/nwpm.py
nwpm/nwpm_exec.py
nwpm-0.1.20.dist-info/METADATA
nwpm-0.1.20.dist-info/WHEEL
nwpm-0.1.20.dist-info/entry_points.txt
nwpm-0.1.20.dist-info/top_level.txt
nwpm-0.1.20.dist-info/RECORD
