Metadata-Version: 2.1
Name: nwpm
Version: 0.1.20
Summary: Navigator Workspace Pack Manager
Home-page: https://github.com/xkevas24/nwpm
Author: Alan Hsu
Author-email: xkevas@qq.com
License: Apache-2.0 License
Keywords: nwpm,navigator,workspace_pack
Platform: UNKNOWN
Requires-Python: >=3.6
Requires-Dist: pyinstaller
Requires-Dist: requests
Requires-Dist: zipp
Requires-Dist: urllib3
